[
  {
    "chainId": 11155111,
    "address": "0x1c7D4B196Cb0C7B01d743Fbc6116a902379C7238",
    "name": "Native USDC",
    "symbol": "USDC",
    "decimals": 6,
    "logoURI": "https://assets.coingecko.com/coins/images/6319/standard/usdc.png",
    "cctp": true
  },
  {
    "chainId": 11155420,
    "address": "0x5fd84259d66Cd46123540766Be93DFE6D43130D7",
    "name": "Native USDC",
    "symbol": "USDC",
    "decimals": 6,
    "logoURI": "https://assets.coingecko.com/coins/images/6319/standard/usdc.png",
    "cctp": true
  },
  {
    "chainId": 84532,
    "address": "0x036CbD53842c5426634e7929541eC2318f3dCF7e",
    "name": "Native USDC",
    "symbol": "USDC",
    "decimals": 6,
    "logoURI": "https://assets.coingecko.com/coins/images/6319/standard/usdc.png",
    "cctp": true
  },
  {
    "chainId": 8453,
    "address": "0xDeadDeAddeAddEAddeadDEaDDEAdDeaDDeAD0000",
    "name": "Ether",
    "symbol": "ETH",
    "decimals": 18,
    "logoURI": "https://ethereum-optimism.github.io/data/ETH/logo.svg"
  }
]
